cluseek/__init__.py
cluseek/__main__.py
cluseek/about.py
cluseek/dbdl.py
cluseek/dframe.py
cluseek/uiqt.py
cluseek/diamond/diamond-linux64-2
cluseek/diamond/diamond-osx-arm64
cluseek/diamond/diamond-win64.exe
cluseek/uilayouts/ClusterNetworkViewer2.py
cluseek/uilayouts/ClusterStorage.py
cluseek/uilayouts/NeiviewLegend.py
cluseek/uilayouts/__init__.py
cluseek/uilayouts/about_neiview.py
cluseek/uilayouts/accsetblock.py
cluseek/uilayouts/blastconfig.py
cluseek/uilayouts/clusterinfo.py
cluseek/uilayouts/colocresultsframe.py
cluseek/uilayouts/constraintsframe.py
cluseek/uilayouts/dbprogressbar.py
cluseek/uilayouts/excelexportframe.py
cluseek/uilayouts/exportframe.py
cluseek/uilayouts/featureinfo.py
cluseek/uilayouts/filewidget.py
cluseek/uilayouts/graphframe.py
cluseek/uilayouts/importframe.py
cluseek/uilayouts/info_cluster.py
cluseek/uilayouts/info_feature.py
cluseek/uilayouts/info_protein.py
cluseek/uilayouts/info_region.py
cluseek/uilayouts/info_sequence.py
cluseek/uilayouts/info_taxon.py
cluseek/uilayouts/introwindow.py
cluseek/uilayouts/neiconfig.py
cluseek/uilayouts/neiexport.py
cluseek/uilayouts/neiview.py
cluseek/uilayouts/neiview_creator.py
cluseek/uilayouts/proteingrouptable.py
cluseek/uilayouts/proteininfo.py
cluseek/uilayouts/regioninfo.py
cluseek/uilayouts/resources.py
cluseek/uilayouts/selection_manager.py
cluseek/uilayouts/selector_widget.py
cluseek/uilayouts/styledictcreator.py
cluseek/uilayouts/tag_widget.py
cluseek/uilayouts/taginfowidget.py
cluseek/uilayouts/tagwidget.py
cluseek/uilayouts/taxoninfo.py
cluseek/uilayouts/wrapperwindow.py
cluseek-2.0.2.dist-info/LICENSE
cluseek-2.0.2.dist-info/METADATA
cluseek-2.0.2.dist-info/WHEEL
cluseek-2.0.2.dist-info/entry_points.txt
cluseek-2.0.2.dist-info/top_level.txt
cluseek-2.0.2.dist-info/RECORD
