Metadata-Version: 2.1
Name: cluseek
Version: 2.0.2
Summary: A GUI application for the discovery and analysis of gene clusters.
Home-page: UNKNOWN
Author: OndrejHrebicek
Author-email: cluseek@biomed.cas.cz
License: MIT
Platform: UNKNOWN
Requires-Dist: biopython==1.79
Requires-Dist: matplotlib
Requires-Dist: openpyxl==3.0.10
Requires-Dist: PySide2==5.15.2.1
Requires-Dist: networkx==3.2.1
